ultraconfiguration/__init__.py
ultraconfiguration/manager.py
ultraconfiguration-1.2.0.dist-info/LICENSE.rst
ultraconfiguration-1.2.0.dist-info/METADATA
ultraconfiguration-1.2.0.dist-info/WHEEL
ultraconfiguration-1.2.0.dist-info/top_level.txt
ultraconfiguration-1.2.0.dist-info/RECORD
